calc_please/__init__.py
calc_please-0.0.1.dist-info/METADATA
calc_please-0.0.1.dist-info/WHEEL
calc_please-0.0.1.dist-info/RECORD
