Metadata-Version: 2.1
Name: calc-please
Version: 0.0.1
Summary: Simple cli for genai project management
Author: Luke Lalor
Author-email: lukehlalor@gmail.com
Requires-Python: >=3.10,<4.0
Classifier: Programming Language :: Python :: 3
Classifier: Programming Language :: Python :: 3.10
Classifier: Programming Language :: Python :: 3.11
Classifier: Programming Language :: Python :: 3.12
